ipythontutor/__init__.py
ipythontutor/ipythontutor.py
ipythontutor/version.py
ipythontutor-0.4.0.dist-info/METADATA
ipythontutor-0.4.0.dist-info/WHEEL
ipythontutor-0.4.0.dist-info/RECORD
