Metadata-Version: 2.4
Name: ipythontutor
Version: 0.4.0
Summary: An extension for IPython to embed a pythontutor iframe
Project-URL: Homepage, https://github.com/parmentelat/ipythontutor
Author-email: Thierry Parmentelat <thierry.parmentelat@inria.fr>
License: CC-BY-NC-4.0
Keywords: IPython,Jupyter,Python,notebook,pythontutor
Requires-Python: >=3.10
Requires-Dist: ipython
